hyperon_das_atomdb_cpp/__init__.py
hyperon_das_atomdb_cpp/adapters/__init__.py
hyperon_das_atomdb_cpp/constants/__init__.py
hyperon_das_atomdb_cpp/database/__init__.py
hyperon_das_atomdb_cpp/document_types/__init__.py
hyperon_das_atomdb_cpp/exceptions/__init__.py
hyperon_das_atomdb_cpp/ext.so
hyperon_das_atomdb_cpp-0.10.1.dist-info/WHEEL
hyperon_das_atomdb_cpp-0.10.1.dist-info/METADATA
hyperon_das_atomdb_cpp-0.10.1.dist-info/RECORD
